minimalKNN.cpython-39-x86_64-linux-gnu.so
minimalKNN-0.9.dist-info/LICENSE
minimalKNN-0.9.dist-info/METADATA
minimalKNN-0.9.dist-info/WHEEL
minimalKNN-0.9.dist-info/top_level.txt
minimalKNN-0.9.dist-info/RECORD
