Metadata-Version: 2.1
Name: minimalKNN
Version: 0.9
Summary: MinimalKNN: minimal package to construct k-NN Graph
Home-page: https://bitbucket.org/ryou_ohsawa/minimalKNN/src/master/
Author: Ryou Ohsawa
Author-email: ohsawa@ioa.s.u-tokyo.ac.jp
Maintainer: Ryou Ohsawa
Maintainer-email: ohsawa@ioa.s.u-tokyo.ac.jp
License: MIT
Platform: UNKNOWN
Classifier: Development Status :: 3 - Alpha
Classifier: Environment :: Console
Classifier: Intended Audience :: Science/Research
Classifier: License :: OSI Approved :: MIT License
Classifier: Operating System :: POSIX :: Linux
Classifier: Programming Language :: Python :: 3
Classifier: Programming Language :: Python :: 3.7
Classifier: Programming Language :: Python :: Implementation :: CPython
Classifier: Topic :: Scientific/Engineering :: Astronomy
License-File: LICENSE
Requires-Dist: cython (>=0.22)
Requires-Dist: numpy (>=1.22)
Requires-Dist: matplotlib (>=3.5)
Requires-Dist: wheel (>=0.37)
